AUTHORS.rst
LICENSE.txt
README.md
pyproject.toml
src/dppd_plotnine/__init__.py
src/dppd_plotnine/dppd_plotnine.py
src/dppd_plotnine/plotnine_extensions.py
src/dppd_plotnine.egg-info/PKG-INFO
src/dppd_plotnine.egg-info/SOURCES.txt
src/dppd_plotnine.egg-info/dependency_links.txt
src/dppd_plotnine.egg-info/requires.txt
src/dppd_plotnine.egg-info/top_level.txt
src/dppd_plotnine/geoms/__init__.py
src/dppd_plotnine/geoms/annotation_stripes_dppd.py
tests/test_annotations.py
tests/test_dppd_plotnine.py
tests/test_extensions.py