Metadata-Version: 2.4
Name: dppd-plotnine
Version: 0.2.9
Summary: Combines plotnine and dppd
Author-email: Florian Finkernagel <finkernagel@imt.uni-marburg.de>
License: The MIT License (MIT)
Project-URL: Repository, https://github.com/TyberiusPrime/dppd_plotnine
Requires-Python: >=3.12
License-File: LICENSE.txt
License-File: AUTHORS.rst
Requires-Dist: plotnine>=0.13
Requires-Dist: mizani>=0.13
Requires-Dist: dppd
Provides-Extra: dev
Requires-Dist: build; extra == "dev"
Requires-Dist: numpydoc; extra == "dev"
Requires-Dist: plotnine; extra == "dev"
Requires-Dist: pytest; extra == "dev"
Requires-Dist: pytest-cov; extra == "dev"
Requires-Dist: sphinx; extra == "dev"
Requires-Dist: sphinx-bootstrap-theme; extra == "dev"
Requires-Dist: ruff; extra == "dev"
Dynamic: license-file
